README.rst
setup.py
TwistChat.egg-info/PKG-INFO
TwistChat.egg-info/SOURCES.txt
TwistChat.egg-info/dependency_links.txt
TwistChat.egg-info/entry_points.txt
TwistChat.egg-info/requires.txt
TwistChat.egg-info/top_level.txt
twistchat/__init__.py
twistchat/misc.py
twistchat/server.py