Metadata-Version: 1.1
Name: TwistChat
Version: 0.1.1
Summary: Chatroom server written using Twisted
Home-page: https://bede.club/tag/chatroom
Author: Bede Kelly
Author-email: admin@bede.club
License: The Unlicense
Keywords: irc,chatroom,server,webchat
Platform: UNKNOWN
Classifier: Development Status :: 4 - Beta
Classifier: Environment :: Console
Classifier: Operating System :: POSIX
Classifier: Programming Language :: Python
Classifier: Topic :: Communications
Classifier: Topic :: Communications :: Chat :: Internet Relay Chat
